mkslug/__init__.py
mkslug/__main__.py
mkslug-1.1.2.dist-info/LICENSE
mkslug-1.1.2.dist-info/METADATA
mkslug-1.1.2.dist-info/WHEEL
mkslug-1.1.2.dist-info/top_level.txt
mkslug-1.1.2.dist-info/RECORD
